LICENSE
README.md
setup.py
filecloudsync/__init__.py
filecloudsync/file.py
filecloudsync.egg-info/PKG-INFO
filecloudsync.egg-info/SOURCES.txt
filecloudsync.egg-info/dependency_links.txt
filecloudsync.egg-info/requires.txt
filecloudsync.egg-info/top_level.txt
filecloudsync/s3/__init__.py
filecloudsync/s3/core.py
filecloudsync/s3/exceptions.py
filecloudsync/s3/monitor.py
tests/__init__.py
tests/etag.py
tests/test_sync.py
tests/test_sync2.py