Metadata-Version: 2.1
Name: filecloudsync
Version: 0.0.16
Summary: A method to synchronize files from several file cloud systems. At the moment, only S3 is implemented. Any help is welcome.
Home-page: https://github.com/jmgomezsoriano/filecloudsync
Author: José Manuel Gómez Soriano
Author-email: jmgomez.soriano@gmail.com
License: GPL v3
Classifier: Programming Language :: Python :: 3
Classifier: License :: OSI Approved :: MIT License
Classifier: Operating System :: OS Independent
Requires-Python: >=3.7,<4
License-File: LICENSE
Requires-Dist: PyYAML<7,>=5.4.1
Requires-Dist: boto3<2,>=1.34.34
Requires-Dist: mysmallutils<3,>=2.0.17
